loggerbase/__init__.py
loggerbase/_static.py
loggerbase/_tables.py
loggerbase/conf.py
loggerbase/database.py
loggerbase/enums.py
loggerbase/exceptions.py
loggerbase/loggerbase.py
loggerbase/models.py
tests/__init__.py
tests/test_conf.py
loggerbase-0.0.2.dist-info/METADATA
loggerbase-0.0.2.dist-info/WHEEL
loggerbase-0.0.2.dist-info/top_level.txt
loggerbase-0.0.2.dist-info/RECORD
